fapshi/__init__.py
fapshi/client.py
fapshi/exceptions.py
fapshi/models.py
fapshi/utils.py
fapshi-1.0.0.dist-info/licenses/LICENSE
fapshi-1.0.0.dist-info/METADATA
fapshi-1.0.0.dist-info/WHEEL
fapshi-1.0.0.dist-info/top_level.txt
fapshi-1.0.0.dist-info/RECORD
