Metadata-Version: 2.4
Name: fapshi
Version: 1.0.0
Summary: Python SDK for the Fapshi Payment API
Home-page: https://github.com/Fapshi/python-sdk
Author: Fapshi
Author-email: signeeric9@gmail.com
License: MIT
Keywords: fapshi,payment,api,sdk
Classifier: Development Status :: 3 - Alpha
Classifier: Intended Audience :: Developers
Classifier: License :: OSI Approved :: MIT License
Classifier: Programming Language :: Python :: 3
Classifier: Programming Language :: Python :: 3.7
Classifier: Programming Language :: Python :: 3.8
Classifier: Programming Language :: Python :: 3.9
Classifier: Programming Language :: Python :: 3.10
Classifier: Programming Language :: Python :: 3.11
Classifier: Topic :: Software Development :: Libraries :: Python Modules
Requires-Python: >=3.7
License-File: LICENSE
Requires-Dist: requests>=2.25.0
Provides-Extra: dev
Requires-Dist: pytest>=6.0.0; extra == "dev"
Requires-Dist: pytest-cov>=2.0.0; extra == "dev"
Requires-Dist: black>=21.0.0; extra == "dev"
Requires-Dist: flake8>=3.8.0; extra == "dev"
Requires-Dist: mypy>=0.800; extra == "dev"
Dynamic: author-email
Dynamic: home-page
Dynamic: license-file
Dynamic: requires-python
